{
  "as_of": "2026-07-14",
  "due": [
    {
      "action": "metadata_version_and_digest_check",
      "monitor_interval_days": 1,
      "monitor_profile": "clinical_guideline",
      "next_monitor_at": "2026-07-14",
      "source_id": "source.bts.chronic-cough.2023"
    },
    {
      "action": "metadata_version_and_digest_check",
      "monitor_interval_days": 1,
      "monitor_profile": "clinical_guideline",
      "next_monitor_at": "2026-07-14",
      "source_id": "source.ers.chronic-cough.2020"
    },
    {
      "action": "metadata_version_and_digest_check",
      "monitor_interval_days": 1,
      "monitor_profile": "clinical_guideline",
      "next_monitor_at": "2026-07-14",
      "source_id": "source.gina.summary.2025"
    }
  ],
  "network_actions_executed": false,
  "policy_id": "policy.knowledge-refresh",
  "policy_version": "0.2.0",
  "review_status": "unreviewed",
  "upcoming": [
    {
      "action": "metadata_version_and_digest_check",
      "monitor_interval_days": 7,
      "monitor_profile": "public_health_guidance",
      "next_monitor_at": "2026-07-20",
      "source_id": "source.cdc.common-cold.2026"
    },
    {
      "action": "metadata_version_and_digest_check",
      "monitor_interval_days": 7,
      "monitor_profile": "nice_guidance",
      "next_monitor_at": "2026-07-20",
      "source_id": "source.nice.ng120"
    }
  ]
}
